{
  "Babyset": [
    { "src": "/Baby/POST.webp", "height": "h-[250px]" },
    { "src": "/Baby/Baby1.webp", "height": "h-[250px]" },
    { "src": "/Baby/baby2.jpg", "height": "h-[300px]" },
    { "src": "/Baby/baby3.jpg", "height": "h-[350px]" },
    { "src": "/Baby/baby4.jpg", "height": "h-[250px]" },
    { "src": "/Baby/baby5.jpg", "height": "h-[300px]" },
    { "src": "/Baby/baby6.jpg", "height": "h-[350px]" },
    { "src": "/Baby/aaNDAL/01.webp", "height": "h-[250px]" },
    { "src": "/Baby/aaNDAL/02.webp", "height": "h-[300px]" },
    { "src": "/Baby/aaNDAL/03.webp", "height": "h-[350px]" },
    { "src": "/Baby/aaNDAL/04.webp", "height": "h-[250px]" },
    { "src": "/Baby/aaNDAL/05.webp", "height": "h-[300px]" },
    { "src": "/Baby/aaNDAL/06.webp", "height": "h-[350px]" }]
}
